{
	"olives":
  [{
    "oliveType": "Kalamon",
    "color": "black",
    "treeId": 1541528150902,
    "kg": 39
  },
  {
    "oliveType": "Kalamon",
    "color": "black",
    "treeId": 1541528150915,
    "kg": 144
  },
  {
    "oliveType": "Kalamon",
    "color": "black",
    "treeId": 1541528150920,
    "kg": 439
  },
  {
    "oliveType": "Cerignola",
    "color": "green",
    "treeId": 1541528150909,
    "kg": 31
  },
  {
    "oliveType": "Kalamon",
    "color": "black",
    "treeId": 1541528150950,
    "kg": 73
  }
]
}